CHANGELOG.md
ekrhizoc/bot/base_crawler.py
ekrhizoc/bot/crawlers/__init__.py
ekrhizoc/bot/crawlers/universal_bfs.py
ekrhizoc/bot/helpers/url_utils.py
ekrhizoc/cli/__main__.py
ekrhizoc/cli/base_command.py
ekrhizoc/cli/commands/__init__.py
ekrhizoc/cli/commands/crawl.py
ekrhizoc/logger.py
ekrhizoc/settings.py
ekrhizoc-0.1.2.dist-info/entry_points.txt
ekrhizoc-0.1.2.dist-info/LICENSE
ekrhizoc-0.1.2.dist-info/WHEEL
ekrhizoc-0.1.2.dist-info/METADATA
ekrhizoc-0.1.2.dist-info/RECORD
